MANIFEST.in
README.md
setup.py
test/__init__.py
test/config.yml.templ
test/test_client.py
test/test_collection.py
test/test_sso.py
uservoice/__init__.py
uservoice/client.py
uservoice/collection.py
uservoice/sso.py
uservoice.egg-info/PKG-INFO
uservoice.egg-info/SOURCES.txt
uservoice.egg-info/dependency_links.txt
uservoice.egg-info/requires.txt
uservoice.egg-info/top_level.txt