Metadata-Version: 2.1
Name: uservoice
Version: 0.0.25
Summary: UserVoice Python library
Home-page: http://pypi.python.org/pypi/uservoice/
Author: UserVoice Inc.
Author-email: dev@uservoice.com
License: MIT
Platform: UNKNOWN
